Metadata-Version: 2.1
Name: izh2114
Version: 0.0
Summary: Numerical methods
Home-page: UNKNOWN
Author-email: ustinovkirill23@gmail.com
License: UNKNOWN
Platform: UNKNOWN
